jabutiles/__init__.py
jabutiles/base.py
jabutiles/configs.py
jabutiles/convert.py
jabutiles/layer.py
jabutiles/mask.py
jabutiles/maskgen.py
jabutiles/shade.py
jabutiles/texture.py
jabutiles/tile.py
jabutiles/utils.py
jabutiles/utils_img.py
jabutiles-0.1.2.dist-info/METADATA
jabutiles-0.1.2.dist-info/WHEEL
jabutiles-0.1.2.dist-info/licenses/LICENSE
jabutiles-0.1.2.dist-info/RECORD
